spira_xunit_reader.py
spira_addons_xunit-1.0.0.dist-info/LICENSE
spira_addons_xunit-1.0.0.dist-info/METADATA
spira_addons_xunit-1.0.0.dist-info/WHEEL
spira_addons_xunit-1.0.0.dist-info/entry_points.txt
spira_addons_xunit-1.0.0.dist-info/top_level.txt
spira_addons_xunit-1.0.0.dist-info/RECORD
