Metadata-Version: 2.1
Name: spira-addons-xunit
Version: 1.0.0
Summary: Exports xUnit format test executions as test runs in Spira (SpiraTest/Team/Plan)
Home-page: http://www.inflectra.com/SpiraTest/Integrations/Unit-Test-Frameworks.aspx
Author: Inflectra Corporation
Author-email: support@inflectra.com
Classifier: Framework :: Pytest
Classifier: Topic :: Software Development :: Testing
Classifier: Programming Language :: Python :: 3
Classifier: Operating System :: OS Independent
License-File: LICENSE
